Wlyrics/__init__.py
Wlyrics/lyrics.py
Wlyrics_W4lk3r-0.1.21.dist-info/METADATA
Wlyrics_W4lk3r-0.1.21.dist-info/WHEEL
Wlyrics_W4lk3r-0.1.21.dist-info/top_level.txt
Wlyrics_W4lk3r-0.1.21.dist-info/RECORD
