Metadata-Version: 2.1
Name: Wlyrics-W4lk3r
Version: 0.1.21
Summary: song lyrics pip by W4lk3r
Home-page: https://github.com/Walker-00/Wlyrics
Author: W4lk3r
Author-email: w000alker@gmail.com
License: UNKNOWN
Project-URL: Bug Tracker, https://github.com/Walker-00/Wlyrics/issues
Keywords: song lyrics,music lyrics,lyrics
Platform: UNKNOWN
Classifier: Programming Language :: Python :: 3
Classifier: License :: OSI Approved :: MIT License
Classifier: Operating System :: Unix
Classifier: Operating System :: MacOS :: MacOS X
Classifier: Operating System :: Microsoft :: Windows
Requires-Python: >=3.6
Requires-Dist: requests
